hihelper_make_password/__init__.py
hihelper_make_password/make_password.py
hihelper_make_password-0.2.dist-info/METADATA
hihelper_make_password-0.2.dist-info/WHEEL
hihelper_make_password-0.2.dist-info/top_level.txt
hihelper_make_password-0.2.dist-info/RECORD
