Metadata-Version: 2.1
Name: hihelper_make_password
Version: 0.2
Summary: password maker
Home-page: https://github.com/hihelper/hihelper_make_password
Author: ssagghnnam
Author-email: ssagghnnam@gmail.com
Classifier: Programming Language :: Python :: 3
Classifier: License :: OSI Approved :: MIT License
Classifier: Operating System :: OS Independent
Requires-Python: >=3.6
